sobolev_alignment/__init__.py
sobolev_alignment/_scvi_default_params.py
sobolev_alignment/feature_analysis.py
sobolev_alignment/generate_artificial_sample.py
sobolev_alignment/interpolated_features.py
sobolev_alignment/kernel_operations.py
sobolev_alignment/krr_approx.py
sobolev_alignment/krr_model_selection.py
sobolev_alignment/multi_krr_approx.py
sobolev_alignment/scvi_model_search.py
sobolev_alignment/sobolev_alignment.py
sobolev_alignment-1.0.0.dist-info/METADATA
sobolev_alignment-1.0.0.dist-info/WHEEL
sobolev_alignment-1.0.0.dist-info/licenses/LICENSE
sobolev_alignment-1.0.0.dist-info/RECORD
