Metadata-Version: 2.1
Name: sobolev_alignment
Version: 1.0.0
Summary: Sobolev alignment of deep probabilistic models for comparing single cell profiles
Project-URL: Documentation, https://sobolev_alignment.readthedocs.io/
Project-URL: Source, https://github.com/saroudant/sobolev_alignment
Project-URL: Home-page, https://github.com/saroudant/sobolev_alignment
Author: Soufiane Mourragui
Maintainer-email: Soufiane Mourragui <soufiane.mourragui@gmail.com>
License: MIT License
License-File: LICENSE
Requires-Python: >=3.8
Requires-Dist: anndata
Requires-Dist: codecov
Requires-Dist: cython
Requires-Dist: hyperopt
Requires-Dist: matplotlib
Requires-Dist: mock
Requires-Dist: numpy
Requires-Dist: pandas
Requires-Dist: scanpy
Requires-Dist: scikit-learn
Requires-Dist: scipy
Requires-Dist: scvi-tools
Requires-Dist: session-info
Requires-Dist: torch
Provides-Extra: dev
Requires-Dist: bump2version; extra == 'dev'
Requires-Dist: pre-commit; extra == 'dev'
Requires-Dist: twine>=4.0.2; extra == 'dev'
Provides-Extra: doc
Requires-Dist: ipykernel; extra == 'doc'
Requires-Dist: ipython; extra == 'doc'
Requires-Dist: myst-nb; extra == 'doc'
Requires-Dist: sphinx-autodoc-typehints; extra == 'doc'
Requires-Dist: sphinx-book-theme>=1.0.0; extra == 'doc'
Requires-Dist: sphinx-copybutton; extra == 'doc'
Requires-Dist: sphinx>=4; extra == 'doc'
Requires-Dist: sphinxcontrib-bibtex>=1.0.0; extra == 'doc'
Provides-Extra: test
Requires-Dist: pytest; extra == 'test'
Requires-Dist: pytest-cov; extra == 'test'
